chinaunicom_ai/__init__.py
chinaunicom_ai/algorithm_toolbox.py
chinaunicom_ai/asr_toolbox.py
chinaunicom_ai/chromadb_toolbox.py
chinaunicom_ai/container_toolbox.py
chinaunicom_ai/dify_toolbox.py
chinaunicom_ai-0.9.1.dist-info/LICENSE
chinaunicom_ai-0.9.1.dist-info/METADATA
chinaunicom_ai-0.9.1.dist-info/WHEEL
chinaunicom_ai-0.9.1.dist-info/top_level.txt
chinaunicom_ai-0.9.1.dist-info/RECORD
