Metadata-Version: 2.1
Name: chinaunicom-ai
Version: 0.9.1
Summary: 山东联通产互AI工具箱
Home-page: https://github.com/yourusername/your-package
Author: zhaoyongzheng
Author-email: 17668860550@163.com
Classifier: Programming Language :: Python :: 3
Classifier: License :: OSI Approved :: MIT License
Classifier: Operating System :: OS Independent
Requires-Python: >=3.8
License-File: LICENSE
Requires-Dist: docker
Requires-Dist: redis
Requires-Dist: APScheduler
Requires-Dist: python-dateutil
Requires-Dist: addict
Requires-Dist: aiohappyeyeballs
Requires-Dist: aiohttp
Requires-Dist: aiosignal
Requires-Dist: aliyun-python-sdk-core
Requires-Dist: aliyun-python-sdk-kms
Requires-Dist: annotated-types
Requires-Dist: antlr4-python3-runtime
Requires-Dist: anyio
Requires-Dist: async-timeout
Requires-Dist: attrs
Requires-Dist: audioread
Requires-Dist: certifi
Requires-Dist: cffi
Requires-Dist: charset-normalizer
Requires-Dist: click
Requires-Dist: colorama
Requires-Dist: crcmod
Requires-Dist: cryptography
Requires-Dist: datasets
Requires-Dist: decorator
Requires-Dist: dill
Requires-Dist: editdistance
Requires-Dist: exceptiongroup
Requires-Dist: fastapi
Requires-Dist: filelock
Requires-Dist: frozenlist
Requires-Dist: fsspec
Requires-Dist: funasr
Requires-Dist: h11
Requires-Dist: huggingface-hub
Requires-Dist: hydra-core
Requires-Dist: idna
Requires-Dist: importlib-metadata
Requires-Dist: importlib-resources
Requires-Dist: jaconv
Requires-Dist: jamo
Requires-Dist: jieba
Requires-Dist: Jinja2
Requires-Dist: jmespath
Requires-Dist: joblib
Requires-Dist: kaldiio
Requires-Dist: lazy-loader
Requires-Dist: librosa
Requires-Dist: llvmlite
Requires-Dist: MarkupSafe
Requires-Dist: modelscope
Requires-Dist: more-itertools
Requires-Dist: mpmath
Requires-Dist: msgpack
Requires-Dist: multidict
Requires-Dist: multiprocess
Requires-Dist: networkx
Requires-Dist: numba
Requires-Dist: numpy
Requires-Dist: omegaconf
Requires-Dist: openai-whisper
Requires-Dist: oss2
Requires-Dist: packaging
Requires-Dist: pandas
Requires-Dist: pillow
Requires-Dist: platformdirs
Requires-Dist: pooch
Requires-Dist: propcache
Requires-Dist: protobuf
Requires-Dist: pyarrow
Requires-Dist: pycparser
Requires-Dist: pycryptodome
Requires-Dist: pydantic
Requires-Dist: pydantic-core
Requires-Dist: pynndescent
Requires-Dist: pytorch-wpe
Requires-Dist: pytz
Requires-Dist: PyYAML
Requires-Dist: regex
Requires-Dist: requests
Requires-Dist: scikit-learn
Requires-Dist: scipy
Requires-Dist: sentencepiece
Requires-Dist: simplejson
Requires-Dist: six
Requires-Dist: sniffio
Requires-Dist: sortedcontainers
Requires-Dist: soundfile
Requires-Dist: soxr
Requires-Dist: starlette
Requires-Dist: sympy
Requires-Dist: tensorboardX
Requires-Dist: threadpoolctl
Requires-Dist: tiktoken
Requires-Dist: torch
Requires-Dist: torch-complex
Requires-Dist: torchaudio
Requires-Dist: torchvision
Requires-Dist: tqdm
Requires-Dist: typing-extensions
Requires-Dist: tzdata
Requires-Dist: umap-learn
Requires-Dist: urllib3
Requires-Dist: uvicorn
Requires-Dist: xxhash
Requires-Dist: yarl
Requires-Dist: zipp
Requires-Dist: chromadb
